ReliabilityDiagram/ReliabilityDiagram.py
ReliabilityDiagram/__init__.py
ReliabilityDiagram-0.0.3.dist-info/LICENSE
ReliabilityDiagram-0.0.3.dist-info/METADATA
ReliabilityDiagram-0.0.3.dist-info/WHEEL
ReliabilityDiagram-0.0.3.dist-info/top_level.txt
ReliabilityDiagram-0.0.3.dist-info/RECORD
