Metadata-Version: 2.1
Name: ReliabilityDiagram
Version: 0.0.3
Summary: A package which provides the contingency table and all the other ingredients required to plot a reliability diagram. A reliability diagram is a diagnostic plot which helps to understand the joint distribution of forecasts and observations for probabilistic forecasts of a dichotomous event (i.e., yes/no event).
Home-page: https://github.com/clecoz/ReliabilityDiagram
Author: Naveen Goutham, Camille Le Coz
Author-email: naveen.goutham@outlook.com, camille.lecoz@laposte.net
License: Apache License 2.0
Keywords: reliability table,contingency table,reliability diagram,attributes diagram,reliability,resolution,forecast attributes,brier score,ensemble forecast,forecast,climatology,python
Platform: UNKNOWN
License-File: LICENSE
Requires-Dist: numpy
Requires-Dist: statsmodels
